adafruit_bno08x/__init__.py
adafruit_bno08x/debug.py
adafruit_bno08x/i2c.py
adafruit_bno08x/spi.py
adafruit_bno08x/uart.py
adafruit_circuitpython_bno08x-1.3.0.dist-info/licenses/LICENSE
adafruit_circuitpython_bno08x-1.3.0.dist-info/METADATA
adafruit_circuitpython_bno08x-1.3.0.dist-info/WHEEL
adafruit_circuitpython_bno08x-1.3.0.dist-info/top_level.txt
adafruit_circuitpython_bno08x-1.3.0.dist-info/RECORD
