Metadata-Version: 2.4
Name: adafruit-circuitpython-bno08x
Version: 1.3.0
Summary: Helper library for the Hillcrest Laboratories BNO08x IMUs
Author-email: Adafruit Industries <circuitpython@adafruit.com>
License: MIT
Project-URL: Homepage, https://github.com/adafruit/Adafruit_CircuitPython_BNO08x
Keywords: adafruit,blinka,circuitpython,micropython,bno080,IMU,BNO055,SENSOR,FUSION,VR,MOTION,TRACK,BNO085
Classifier: Intended Audience :: Developers
Classifier: Topic :: Software Development :: Libraries
Classifier: Topic :: Software Development :: Embedded Systems
Classifier: Topic :: System :: Hardware
Classifier: License :: OSI Approved :: MIT License
Classifier: Programming Language :: Python :: 3
License-File: LICENSE
Requires-Dist: Adafruit-Blinka
Requires-Dist: adafruit-circuitpython-busdevice
Provides-Extra: optional
Dynamic: license-file
